{
  "productos": [
    {
      "id": "1",
      "name": "Audifonos",
      "description": "Blanco",
      "category": [
        "Microfonos",
        "Tecnologia"
      ],
      "imagenUrl": "../../assets/img/products/technology/1.jpg",
      "precioventa": 225,
      "precioregular": 345,
      "created_at": "2024-04-30T16:51:07.214X",
      "slug": "tipo-audifonos"
    },
    {
      "id": "2",
      "name": "Microfono gris",
      "description": "Asul",
      "category": [
        "Microfonos",
        "Tecnologia"
      ],
      "imagenUrl": "../../assets/img/products/technology/2.jpg",
      "precioventa": 225,
      "precioregular": 345,
      "created_at": "2024-04-30T16:51:07.214X",
      "slug": "tipo-microfono"
    },
    {
      "id": "3",
      "name": "Computadora",
      "description": "Metalica",
      "category": [
        "Computadoras",
        "Tecnologia"
      ],
      "imagenUrl": "../../assets/img/products/technology/3.jpg",
      "precioventa": 2325,
      "precioregular": 3445,
      "created_at": "2024-04-30T16:51:07.214X",
      "slug": "tipo-computadora"
    },
    {
      "id": "3",
      "name": "Computadora",
      "description": "Metalica",
      "category": [
        "Computadoras",
        "Tecnologia"
      ],
      "imagenUrl": "../../assets/img/products/technology/3.jpg",
      "precioventa": 2325,
      "precioregular": 3445,
      "created_at": "2024-04-30T16:51:07.214X",
      "slug": "tipo-computadora"
    },
    {
      "id": "3",
      "name": "Computadora",
      "description": "Metalica",
      "category": [
        "Computadoras",
        "Tecnologia"
      ],
      "imagenUrl": "../../assets/img/products/technology/3.jpg",
      "precioventa": 2325,
      "precioregular": 3445,
      "created_at": "2024-04-30T16:51:07.214X",
      "slug": "tipo-computadora"
    },
    {
      "id": "3",
      "name": "Computadora",
      "description": "Metalica",
      "category": [
        "Computadoras",
        "Tecnologia"
      ],
      "imagenUrl": "../../assets/img/products/technology/3.jpg",
      "precioventa": 2325,
      "precioregular": 3445,
      "created_at": "2024-04-30T16:51:07.214X",
      "slug": "tipo-computadora"
    },
    {
      "id": "3",
      "name": "Computadora",
      "description": "Metalica",
      "category": [
        "Computadoras",
        "Tecnologia"
      ],
      "imagenUrl": "../../assets/img/products/technology/3.jpg",
      "precioventa": 2325,
      "precioregular": 3445,
      "created_at": "2024-04-30T16:51:07.214X",
      "slug": "tipo-computadora"
    },
    {
      "id": "3",
      "name": "Computadora",
      "description": "Metalica",
      "category": [
        "Computadoras",
        "Tecnologia"
      ],
      "imagenUrl": "../../assets/img/products/technology/3.jpg",
      "precioventa": 2325,
      "precioregular": 3445,
      "created_at": "2024-04-30T16:51:07.214X",
      "slug": "tipo-computadora"
    },
    {
      "id": "3",
      "name": "Computadora",
      "description": "Metalica",
      "category": [
        "Computadoras",
        "Tecnologia"
      ],
      "imagenUrl": "../../assets/img/products/technology/3.jpg",
      "precioventa": 2325,
      "precioregular": 3445,
      "created_at": "2024-04-30T16:51:07.214X",
      "slug": "tipo-computadora"
    },
    {
      "id": "3",
      "name": "Computadora",
      "description": "Metalica",
      "category": [
        "Computadoras",
        "Tecnologia"
      ],
      "imagenUrl": "../../assets/img/products/technology/3.jpg",
      "precioventa": 2325,
      "precioregular": 3445,
      "created_at": "2024-04-30T16:51:07.214X",
      "slug": "tipo-computadora"
    },
    {
      "id": "d32yf86al",
      "name": "dsa",
      "description": "",
      "category": "",
      "precioventa": "",
      "precioregular": "",
      "imagenUrl": "",
      "created_at": "2024-05-23T07:08:09.536Z",
      "slug": ""
    },
    {
      "id": "jbmz9xvu4fl",
      "name": "DSA",
      "description": "",
      "category": "",
      "precioventa": 0,
      "precioregular": 0,
      "imagenUrl": "",
      "created_at": "2024-05-23T19:57:06.367Z",
      "slug": ""
    }
  ]
}